Compiled from "SimpleIfX.java"
public class SimpleIfX {
  public SimpleIfX();
    descriptor: ()V
    Code:
       0: aload_0
       1: invokespecial #1                  // Method java/lang/Object."<init>":()V
       4: return

  public void m(boolean, boolean, boolean, boolean);
    descriptor: (ZZZZ)V
    Code:
       0: getstatic     #2                  // Field java/lang/System.out:Ljava/io/PrintStream;
       3: ldc           #3                  // String Out
       5: invokevirtual #4                  // Method java/io/PrintStream.println:(Ljava/lang/String;)V
       8: iload_1
       9: ifeq          20
      12: iload_2
      13: ifeq          20
      16: iload_3
      17: ifne          25
      20: iload         4
      22: ifeq          33
      25: getstatic     #2                  // Field java/lang/System.out:Ljava/io/PrintStream;
      28: ldc           #5                  // String In
      30: invokevirtual #4                  // Method java/io/PrintStream.println:(Ljava/lang/String;)V
      33: getstatic     #2                  // Field java/lang/System.out:Ljava/io/PrintStream;
      36: ldc           #6                  // String Out:post
      38: invokevirtual #4                  // Method java/io/PrintStream.println:(Ljava/lang/String;)V
      41: return
}
