Classfile /home/jonathan/workspace/Kores-BytecodeReader/src/test/resources/lvl2/SimpleIfElseX.class
  Last modified 30 de jun de 2017; size 667 bytes
  MD5 checksum ea0ca669cc7ca26e9601a2c449947228
  Compiled from "SimpleIfElseX.java"
public class SimpleIfElseX
  minor version: 0
  major version: 52
  flags: (0x0021) ACC_PUBLIC, ACC_SUPER
  this_class: #8                          // SimpleIfElseX
  super_class: #9                         // java/lang/Object
  interfaces: 0, fields: 0, methods: 2, attributes: 1
Constant pool:
   #1 = Methodref          #9.#27         // java/lang/Object."<init>":()V
   #2 = Fieldref           #28.#29        // java/lang/System.out:Ljava/io/PrintStream;
   #3 = String             #30            // Out
   #4 = Methodref          #31.#32        // java/io/PrintStream.println:(Ljava/lang/String;)V
   #5 = String             #33            // In
   #6 = String             #34            // Else
   #7 = String             #35            // Out:post
   #8 = Class              #36            // SimpleIfElseX
   #9 = Class              #37            // java/lang/Object
  #10 = Utf8               <init>
  #11 = Utf8               ()V
  #12 = Utf8               Code
  #13 = Utf8               LineNumberTable
  #14 = Utf8               LocalVariableTable
  #15 = Utf8               this
  #16 = Utf8               LSimpleIfElseX;
  #17 = Utf8               m
  #18 = Utf8               (ZZZZ)V
  #19 = Utf8               a
  #20 = Utf8               Z
  #21 = Utf8               b
  #22 = Utf8               c
  #23 = Utf8               d
  #24 = Utf8               StackMapTable
  #25 = Utf8               SourceFile
  #26 = Utf8               SimpleIfElseX.java
  #27 = NameAndType        #10:#11        // "<init>":()V
  #28 = Class              #38            // java/lang/System
  #29 = NameAndType        #39:#40        // out:Ljava/io/PrintStream;
  #30 = Utf8               Out
  #31 = Class              #41            // java/io/PrintStream
  #32 = NameAndType        #42:#43        // println:(Ljava/lang/String;)V
  #33 = Utf8               In
  #34 = Utf8               Else
  #35 = Utf8               Out:post
  #36 = Utf8               SimpleIfElseX
  #37 = Utf8               java/lang/Object
  #38 = Utf8               java/lang/System
  #39 = Utf8               out
  #40 = Utf8               Ljava/io/PrintStream;
  #41 = Utf8               java/io/PrintStream
  #42 = Utf8               println
  #43 = Utf8               (Ljava/lang/String;)V
{
  public SimpleIfElseX();
    descriptor: ()V
    flags: (0x0001) ACC_PUBLIC
    Code:
      stack=1, locals=1, args_size=1
         0: aload_0
         1: invokespecial #1                  // Method java/lang/Object."<init>":()V
         4: return
      LineNumberTable:
        line 1: 0
      LocalVariableTable:
        Start  Length  Slot  Name   Signature
            0       5     0  this   LSimpleIfElseX;

  public void m(boolean, boolean, boolean, boolean);
    descriptor: (ZZZZ)V
    flags: (0x0001) ACC_PUBLIC
    Code:
      stack=2, locals=5, args_size=5
         0: getstatic     #2                  // Field java/lang/System.out:Ljava/io/PrintStream;
         3: ldc           #3                  // String Out
         5: invokevirtual #4                  // Method java/io/PrintStream.println:(Ljava/lang/String;)V
         8: iload_1
         9: ifeq          20
        12: iload_2
        13: ifeq          20
        16: iload_3
        17: ifne          25
        20: iload         4
        22: ifeq          36
        25: getstatic     #2                  // Field java/lang/System.out:Ljava/io/PrintStream;
        28: ldc           #5                  // String In
        30: invokevirtual #4                  // Method java/io/PrintStream.println:(Ljava/lang/String;)V
        33: goto          44
        36: getstatic     #2                  // Field java/lang/System.out:Ljava/io/PrintStream;
        39: ldc           #6                  // String Else
        41: invokevirtual #4                  // Method java/io/PrintStream.println:(Ljava/lang/String;)V
        44: getstatic     #2                  // Field java/lang/System.out:Ljava/io/PrintStream;
        47: ldc           #7                  // String Out:post
        49: invokevirtual #4                  // Method java/io/PrintStream.println:(Ljava/lang/String;)V
        52: return
      LineNumberTable:
        line 4: 0
        line 5: 8
        line 6: 25
        line 7: 36
        line 8: 44
        line 9: 52
      LocalVariableTable:
        Start  Length  Slot  Name   Signature
            0      53     0  this   LSimpleIfElseX;
            0      53     1     a   Z
            0      53     2     b   Z
            0      53     3     c   Z
            0      53     4     d   Z
      StackMapTable: number_of_entries = 4
        frame_type = 20 /* same */
        frame_type = 4 /* same */
        frame_type = 10 /* same */
        frame_type = 7 /* same */
}
SourceFile: "SimpleIfElseX.java"
