Classfile /home/jonathan/workspace/Kores-BytecodeReader/src/test/resources/ComplexIfTest_ComplexIf_Result.class
  Last modified 3 de jun de 2017; size 809 bytes
  MD5 checksum 9bfc37e7a9de9215133846e9fe92df80
  Compiled from "ComplexIf.cai"
public class test.ComplexIf
  minor version: 0
  major version: 52
  flags: (0x0021) ACC_PUBLIC, ACC_SUPER
  this_class: #2                          // test/ComplexIf
  super_class: #4                         // java/lang/Object
  interfaces: 0, fields: 0, methods: 2, attributes: 1
Constant pool:
   #1 = Utf8               test/ComplexIf
   #2 = Class              #1             // test/ComplexIf
   #3 = Utf8               java/lang/Object
   #4 = Class              #3             // java/lang/Object
   #5 = Utf8               ComplexIf.cai
   #6 = Utf8               <init>
   #7 = Utf8               (ZZZZ)V
   #8 = Utf8               h
   #9 = Utf8               x
  #10 = Utf8               y
  #11 = Utf8               z
  #12 = Utf8               ()V
  #13 = NameAndType        #6:#12         // "<init>":()V
  #14 = Methodref          #4.#13         // java/lang/Object."<init>":()V
  #15 = Utf8               9 < 5
  #16 = String             #15            // 9 < 5
  #17 = Utf8               9 >= 5
  #18 = String             #17            // 9 >= 5
  #19 = Utf8               java/lang/System
  #20 = Class              #19            // java/lang/System
  #21 = Utf8               out
  #22 = Utf8               Ljava/io/PrintStream;
  #23 = NameAndType        #21:#22        // out:Ljava/io/PrintStream;
  #24 = Fieldref           #20.#23        // java/lang/System.out:Ljava/io/PrintStream;
  #25 = Utf8               true
  #26 = String             #25            // true
  #27 = Utf8               java/io/PrintStream
  #28 = Class              #27            // java/io/PrintStream
  #29 = Utf8               println
  #30 = Utf8               (Ljava/lang/String;)V
  #31 = NameAndType        #29:#30        // println:(Ljava/lang/String;)V
  #32 = Methodref          #28.#31        // java/io/PrintStream.println:(Ljava/lang/String;)V
  #33 = Utf8               false
  #34 = String             #33            // false
  #35 = Utf8               b
  #36 = Utf8               Ljava/lang/String;
  #37 = Utf8               a
  #38 = Utf8               Z
  #39 = Utf8               this
  #40 = Utf8               Ltest/ComplexIf;
  #41 = Utf8               java/lang/String
  #42 = Class              #41            // java/lang/String
  #43 = Utf8               <clinit>
  #44 = Utf8               Code
  #45 = Utf8               LocalVariableTable
  #46 = Utf8               LineNumberTable
  #47 = Utf8               StackMapTable
  #48 = Utf8               MethodParameters
  #49 = Utf8               SourceFile
{
  public test.ComplexIf(boolean, boolean, boolean, boolean);
    descriptor: (ZZZZ)V
    flags: (0x0001) ACC_PUBLIC
    Code:
      stack=2, locals=7, args_size=5
         0: aload_0
         1: invokespecial #14                 // Method java/lang/Object."<init>":()V
         4: bipush        9
         6: iconst_5
         7: if_icmpge     14
        10: iconst_1
        11: goto          15
        14: iconst_0
        15: istore        5
        17: bipush        9
        19: iconst_5
        20: if_icmpge     28
        23: ldc           #16                 // String 9 < 5
        25: goto          30
        28: ldc           #18                 // String 9 >= 5
        30: astore        6
        32: iload_1
        33: ifeq          60
        36: iload_2
        37: ifeq          60
        40: iload_3
        41: ifne          49
        44: iload         4
        46: ifeq          60
        49: getstatic     #24                 // Field java/lang/System.out:Ljava/io/PrintStream;
        52: ldc           #26                 // String true
        54: invokevirtual #32                 // Method java/io/PrintStream.println:(Ljava/lang/String;)V
        57: goto          68
        60: getstatic     #24                 // Field java/lang/System.out:Ljava/io/PrintStream;
        63: ldc           #34                 // String false
        65: invokevirtual #32                 // Method java/io/PrintStream.println:(Ljava/lang/String;)V
        68: return
      LocalVariableTable:
        Start  Length  Slot  Name   Signature
           30      39     6     b   Ljava/lang/String;
           15      54     5     a   Z
            0      69     4     z   Z
            0      69     3     y   Z
            0      69     2     x   Z
            0      69     1     h   Z
            0      69     0  this   Ltest/ComplexIf;
      LineNumberTable:
        line 1: 4
        line 4: 10
        line 5: 14
        line 2: 17
        line 6: 23
        line 7: 28
        line 3: 32
        line 8: 49
        line 9: 60
      StackMapTable: number_of_entries = 7
        frame_type = 255 /* full_frame */
          offset_delta = 14
          locals = [ class test/ComplexIf, int, int, int, int ]
          stack = []
        frame_type = 64 /* same_locals_1_stack_item */
          stack = [ int ]
        frame_type = 252 /* append */
          offset_delta = 12
          locals = [ int ]
        frame_type = 65 /* same_locals_1_stack_item */
          stack = [ class java/lang/String ]
        frame_type = 252 /* append */
          offset_delta = 18
          locals = [ class java/lang/String ]
        frame_type = 10 /* same */
        frame_type = 7 /* same */
    MethodParameters:
      Name                           Flags
      h
      x
      y
      z

  static {};
    descriptor: ()V
    flags: (0x0008) ACC_STATIC
    Code:
      stack=0, locals=0, args_size=0
         0: return
}
SourceFile: "ComplexIf.cai"
